LICENSE.md
README.rst
setup.py
fatgoose3/__init__.py
fatgoose3/article.py
fatgoose3/cleaners.py
fatgoose3/configuration.py
fatgoose3/crawler.py
fatgoose3/exceptions.py
fatgoose3/image.py
fatgoose3/network.py
fatgoose3/outputformatters.py
fatgoose3/parsers.py
fatgoose3/text.py
fatgoose3/version.py
fatgoose3/video.py
fatgoose3.egg-info/PKG-INFO
fatgoose3.egg-info/SOURCES.txt
fatgoose3.egg-info/dependency_links.txt
fatgoose3.egg-info/requires.txt
fatgoose3.egg-info/top_level.txt
fatgoose3/extractors/__init__.py
fatgoose3/extractors/authors.py
fatgoose3/extractors/content.py
fatgoose3/extractors/images.py
fatgoose3/extractors/links.py
fatgoose3/extractors/metas.py
fatgoose3/extractors/opengraph.py
fatgoose3/extractors/publishdate.py
fatgoose3/extractors/schema.py
fatgoose3/extractors/tags.py
fatgoose3/extractors/title.py
fatgoose3/extractors/tweets.py
fatgoose3/extractors/videos.py
fatgoose3/resources/images/known-image-css.txt
fatgoose3/resources/text/stopwords-ar.txt
fatgoose3/resources/text/stopwords-da.txt
fatgoose3/resources/text/stopwords-de.txt
fatgoose3/resources/text/stopwords-en.txt
fatgoose3/resources/text/stopwords-es.txt
fatgoose3/resources/text/stopwords-fi.txt
fatgoose3/resources/text/stopwords-fr.txt
fatgoose3/resources/text/stopwords-hu.txt
fatgoose3/resources/text/stopwords-id.txt
fatgoose3/resources/text/stopwords-it.txt
fatgoose3/resources/text/stopwords-ko.txt
fatgoose3/resources/text/stopwords-nb.txt
fatgoose3/resources/text/stopwords-nl.txt
fatgoose3/resources/text/stopwords-no.txt
fatgoose3/resources/text/stopwords-pl.txt
fatgoose3/resources/text/stopwords-pt.txt
fatgoose3/resources/text/stopwords-ru.txt
fatgoose3/resources/text/stopwords-sv.txt
fatgoose3/resources/text/stopwords-zh.txt
fatgoose3/utils/__init__.py
fatgoose3/utils/encoding.py
fatgoose3/utils/images.py